classic/db_tools/__init__.py
classic/db_tools/engine.py
classic/db_tools/exceptions.py
classic/db_tools/params_styles.py
classic/db_tools/pool.py
classic/db_tools/poolvalidators.py
classic/db_tools/scoped_connection.py
classic/db_tools/transaction.py
classic/db_tools/types.py
classic/db_tools/dynamic/__init__.py
classic/db_tools/dynamic/extension.py
classic/db_tools/dynamic/factory.py
classic/db_tools/dynamic/renderer.py
classic/db_tools/mapping/__init__.py
classic/db_tools/mapping/compiler.py
classic/db_tools/mapping/context.py
classic/db_tools/mapping/params.py
classic/db_tools/mapping/render.py
classic/db_tools/mapping/types.py
classic/db_tools/static/__init__.py
classic/db_tools/static/factory.py
classic_db_tools-0.0.4.dist-info/licenses/LICENSE
classic_db_tools-0.0.4.dist-info/METADATA
classic_db_tools-0.0.4.dist-info/WHEEL
classic_db_tools-0.0.4.dist-info/top_level.txt
classic_db_tools-0.0.4.dist-info/RECORD
