Metadata-Version: 2.4
Name: classic-db-tools
Version: 0.0.4
Summary: Classic DB tools
Author-email: Sergey Variasov <variasov@gmail.com>
License-Expression: MIT
Project-URL: Homepage, https://github.com/variasov/classic-db-tools
Keywords: Jinja2,SQL,Python,Template
Classifier: Development Status :: 4 - Beta
Classifier: Environment :: Console
Classifier: Intended Audience :: Developers
Classifier: Operating System :: OS Independent
Classifier: Programming Language :: Python
Classifier: Programming Language :: Python :: 3
Classifier: Programming Language :: Python :: 3.10
Classifier: Programming Language :: Python :: 3 :: Only
Requires-Python: >=3.10
License-File: LICENSE
Requires-Dist: classic-components~=1.3
Requires-Dist: Jinja2~=3.1
Provides-Extra: dev
Requires-Dist: pytest==6.2.5; extra == "dev"
Requires-Dist: psycopg==3.2.1; extra == "dev"
Requires-Dist: sqlfluff==3.4.0; extra == "dev"
Dynamic: license-file
